spinguin/__init__.py
spinguin/_core/__init__.py
spinguin/_core/_basis.py
spinguin/_core/_c_sparse_dot.hpp
spinguin/_core/_cache.py
spinguin/_core/_chem.py
spinguin/_core/_composite_spin_system.py
spinguin/_core/_data_io.py
spinguin/_core/_hamiltonian.py
spinguin/_core/_hide_prints.py
spinguin/_core/_intersect_indices.cp312-win_amd64.pyd
spinguin/_core/_intersect_indices.cpp
spinguin/_core/_la.py
spinguin/_core/_liouvillian.py
spinguin/_core/_nmr_isotopes.py
spinguin/_core/_operators.py
spinguin/_core/_parameters.py
spinguin/_core/_propagation.py
spinguin/_core/_relaxation.py
spinguin/_core/_relaxation_properties.py
spinguin/_core/_sparse_dot.cp312-win_amd64.pyd
spinguin/_core/_sparse_dot.cpp
spinguin/_core/_specutils.py
spinguin/_core/_spin_system.py
spinguin/_core/_states.py
spinguin/_core/_superoperators.py
spinguin/_core/_utils.py
spinguin/sequences/__init__.py
spinguin/sequences/_inversion_recovery.py
spinguin/sequences/_inversion_recovery_fid.py
spinguin/sequences/_pulse_and_acquire.py
spinguin-0.0.4.dist-info/licenses/LICENSE
spinguin-0.0.4.dist-info/METADATA
spinguin-0.0.4.dist-info/WHEEL
spinguin-0.0.4.dist-info/top_level.txt
spinguin-0.0.4.dist-info/RECORD
