Metadata-Version: 2.4
Name: spinguin
Version: 0.0.4
Summary: Spinguin is an intuitive Python package for versatile numerical spin-dynamics simulations.
Author-email: Joni Eronen <joni.eronen@oulu.fi>, Perttu Hilla <perttu.hilla@oulu.fi>
License: MIT License
Requires-Python: >=3.11
License-File: LICENSE
Requires-Dist: numpy>=1.26.4
Requires-Dist: scipy>=1.14.1
Requires-Dist: sympy>=1.13.1
Requires-Dist: joblib>=1.5.1
Dynamic: license-file
